orm1/__init__.py
orm1-0.5.0.dist-info/METADATA
orm1-0.5.0.dist-info/WHEEL
orm1-0.5.0.dist-info/licenses/AUTHORS
orm1-0.5.0.dist-info/licenses/LICENSE
orm1-0.5.0.dist-info/RECORD
